{"type": "FeatureCollection","features": [{"geometry":{"coordinates":[118.9849,33.0254],"type":"Point"},"id":"人防工事.1","type":"Feature","properties":{"ObjName":"人防工事","ORDate":"2023-02-09T16:00:00.000+0000","ObjectID":1,"DeptName1":"金湖县人防办","DeptName3":"金湖县人防办","DeptCode1":"3208310022","DeptName2":"金湖县人防办","DataSource":"","ObjState":"完好","DeptCode2":"3208310022","ObjID":"3208310501000001","DeptCode3":"3208310022","Note":"000001","BGID":"320831001008005"}},{"geometry":{"coordinates":[118.9854,33.0251],"type":"Point"},"id":"人防工事.2","type":"Feature","properties":{"ObjName":"人防工事","ORDate":"2023-02-09T16:00:00.000+0000","ObjectID":2,"DeptName1":"金湖县人防办","DeptName3":"金湖县人防办","DeptCode1":"3208310022","DeptName2":"金湖县人防办","DataSource":"","ObjState":"完好","DeptCode2":"3208310022","ObjID":"3208310501000002","DeptCode3":"3208310022","Note":"000002","BGID":"320831001008005"}},{"geometry":{"coordinates":[118.9997,33.0252],"type":"Point"},"id":"人防工事.3","type":"Feature","properties":{"ObjName":"人防工事","ORDate":"2023-02-09T16:00:00.000+0000","ObjectID":3,"DeptName1":"金湖县人防办","DeptName3":"金湖县人防办","DeptCode1":"3208310022","DeptName2":"金湖县人防办","DataSource":"","ObjState":"完好","DeptCode2":"3208310022","ObjID":"3208310501000003","DeptCode3":"3208310022","Note":"000003","BGID":"320831001005004"}},{"geometry":{"coordinates":[118.9985,33.0252],"type":"Point"},"id":"人防工事.4","type":"Feature","properties":{"ObjName":"人防工事","ORDate":"2023-02-09T16:00:00.000+0000","ObjectID":4,"DeptName1":"金湖县人防办","DeptName3":"金湖县人防办","DeptCode1":"3208310022","DeptName2":"金湖县人防办","DataSource":"","ObjState":"完好","DeptCode2":"3208310022","ObjID":"3208310501000004","DeptCode3":"3208310022","Note":"000004","BGID":"320831001005004"}},{"geometry":{"coordinates":[119.0104,33.0159],"type":"Point"},"id":"人防工事.5","type":"Feature","properties":{"ObjName":"人防工事","ORDate":"2023-02-09T16:00:00.000+0000","ObjectID":5,"DeptName1":"金湖县人防办","DeptName3":"金湖县人防办","DeptCode1":"3208310022","DeptName2":"金湖县人防办","DataSource":"","ObjState":"完好","DeptCode2":"3208310022","ObjID":"3208310501000005","DeptCode3":"3208310022","Note":"000005","BGID":"320831001004001"}},{"geometry":{"coordinates":[119.01,33.0147],"type":"Point"},"id":"人防工事.6","type":"Feature","properties":{"ObjName":"人防工事","ORDate":"2023-02-09T16:00:00.000+0000","ObjectID":9,"DeptName1":"金湖县人防办","DeptName3":"金湖县人防办","DeptCode1":"3208310022","DeptName2":"金湖县人防办","DataSource":"","ObjState":"完好","DeptCode2":"3208310022","ObjID":"3208310501000009","DeptCode3":"3208310022","Note":"000009","BGID":"320831001004001"}},{"geometry":{"coordinates":[119.0211,33.0254],"type":"Point"},"id":"人防工事.7","type":"Feature","properties":{"ObjName":"人防工事","ORDate":"2023-02-09T16:00:00.000+0000","ObjectID":7,"DeptName1":"金湖县人防办","DeptName3":"金湖县人防办","DeptCode1":"3208310022","DeptName2":"金湖县人防办","DataSource":"","ObjState":"完好","DeptCode2":"3208310022","ObjID":"3208310501000007","DeptCode3":"3208310022","Note":"000007","BGID":"320831001002002"}},{"geometry":{"coordinates":[119.0163,33.0174],"type":"Point"},"id":"人防工事.8","type":"Feature","properties":{"ObjName":"人防工事","ORDate":"2023-02-09T16:00:00.000+0000","ObjectID":6,"DeptName1":"金湖县人防办","DeptName3":"金湖县人防办","DeptCode1":"3208310022","DeptName2":"金湖县人防办","DataSource":"","ObjState":"完好","DeptCode2":"3208310022","ObjID":"3208310501000006","DeptCode3":"3208310022","Note":"000006","BGID":"320831001002010"}},{"geometry":{"coordinates":[119.0246,33.0147],"type":"Point"},"id":"人防工事.9","type":"Feature","properties":{"ObjName":"人防工事","ORDate":"2023-02-09T16:00:00.000+0000","ObjectID":8,"DeptName1":"金湖县人防办","DeptName3":"金湖县人防办","DeptCode1":"3208310022","DeptName2":"金湖县人防办","DataSource":"","ObjState":"完好","DeptCode2":"3208310022","ObjID":"3208310501000008","DeptCode3":"3208310022","Note":"000008","BGID":"320831001002017"}}]}