{"type": "FeatureCollection","features": [{"geometry":{"coordinates":[119.0006,33.029],"type":"Point"},"id":"信息亭.1","type":"Feature","properties":{"ObjName":"信息亭","ORDate":"2023-02-10T16:00:00.000+0000","ObjectID":1,"DeptName1":"","DeptName3":"","DeptCode1":"","DeptName2":"","DataSource":"","ObjState":"完好","DeptCode2":"","ObjID":"3208310143000001","DeptCode3":"","Note":"000001","BGID":"320831001005002"}},{"geometry":{"coordinates":[119.0009,33.029],"type":"Point"},"id":"信息亭.2","type":"Feature","properties":{"ObjName":"信息亭","ORDate":"2023-02-10T16:00:00.000+0000","ObjectID":2,"DeptName1":"","DeptName3":"","DeptCode1":"","DeptName2":"","DataSource":"","ObjState":"完好","DeptCode2":"","ObjID":"3208310143000002","DeptCode3":"","Note":"000002","BGID":"320831001005002"}},{"geometry":{"coordinates":[119.0016,33.029],"type":"Point"},"id":"信息亭.3","type":"Feature","properties":{"ObjName":"信息亭","ORDate":"2023-02-10T16:00:00.000+0000","ObjectID":4,"DeptName1":"","DeptName3":"","DeptCode1":"","DeptName2":"","DataSource":"","ObjState":"完好","DeptCode2":"","ObjID":"3208310143000004","DeptCode3":"","Note":"000004","BGID":"320831001005003"}},{"geometry":{"coordinates":[119.0017,33.029],"type":"Point"},"id":"信息亭.4","type":"Feature","properties":{"ObjName":"信息亭","ORDate":"2023-02-10T16:00:00.000+0000","ObjectID":5,"DeptName1":"","DeptName3":"","DeptCode1":"","DeptName2":"","DataSource":"","ObjState":"完好","DeptCode2":"","ObjID":"3208310143000005","DeptCode3":"","Note":"000005","BGID":"320831001005003"}},{"geometry":{"coordinates":[119.002,33.029],"type":"Point"},"id":"信息亭.5","type":"Feature","properties":{"ObjName":"信息亭","ORDate":"2023-02-10T16:00:00.000+0000","ObjectID":6,"DeptName1":"","DeptName3":"","DeptCode1":"","DeptName2":"","DataSource":"","ObjState":"完好","DeptCode2":"","ObjID":"3208310143000006","DeptCode3":"","Note":"000006","BGID":"320831001005003"}},{"geometry":{"coordinates":[119.0128,33.0193],"type":"Point"},"id":"信息亭.6","type":"Feature","properties":{"ObjName":"信息亭","ORDate":"2023-02-10T16:00:00.000+0000","ObjectID":3,"DeptName1":"","DeptName3":"","DeptCode1":"","DeptName2":"","DataSource":"","ObjState":"完好","DeptCode2":"","ObjID":"3208310143000003","DeptCode3":"","Note":"000003","BGID":"320831001004007"}}]}