{"type": "FeatureCollection","features": [{"geometry":{"coordinates":[118.9903,33.0237],"type":"Point"},"id":"特殊立杆.1","type":"Feature","properties":{"ObjName":"特殊立杆","ORDate":"2023-02-09T16:00:00.000+0000","ObjectID":1,"DeptName1":"金湖县城管局","DeptName3":"金湖县各私有产权单位","DeptCode1":"3208310003","DeptName2":"金湖县各私有产权单位","DataSource":"","ObjState":"完好","DeptCode2":"","ObjID":"3208310133000001","DeptCode3":"","Note":"000001","BGID":"320831001007038"}}]}