{"type": "FeatureCollection","features": [{"geometry":{"coordinates":[118.9987,33.0175],"type":"Point"},"id":"网络井盖.1","type":"Feature","properties":{"ObjName":"网络井盖","ORDate":"2023-02-09T16:00:00.000+0000","ObjectID":1,"DeptName1":"金湖县各电信运营商","DeptName3":"金湖县各电信运营商","DeptCode1":"3208310028","DeptName2":"金湖县各电信运营商","DataSource":"","ObjState":"完好","DeptCode2":"","ObjID":"3208310109000001","DeptCode3":"","Note":"000001","BGID":"320831001005016"}},{"geometry":{"coordinates":[118.9987,33.0167],"type":"Point"},"id":"网络井盖.2","type":"Feature","properties":{"ObjName":"网络井盖","ORDate":"2023-02-09T16:00:00.000+0000","ObjectID":2,"DeptName1":"金湖县各电信运营商","DeptName3":"金湖县各电信运营商","DeptCode1":"3208310028","DeptName2":"金湖县各电信运营商","DataSource":"","ObjState":"完好","DeptCode2":"","ObjID":"3208310109000002","DeptCode3":"","Note":"000002","BGID":"320831001005016"}}]}